pytest_yaml/__init__.py
pytest_yaml/plugin.py
pytest_yaml-1.2.1.dist-info/LICENSE
pytest_yaml-1.2.1.dist-info/METADATA
pytest_yaml-1.2.1.dist-info/WHEEL
pytest_yaml-1.2.1.dist-info/entry_points.txt
pytest_yaml-1.2.1.dist-info/top_level.txt
pytest_yaml-1.2.1.dist-info/RECORD
